chuk_mcp_math/__init__.py
chuk_mcp_math/advanced_operations.py
chuk_mcp_math/constants.py
chuk_mcp_math/conversion.py
chuk_mcp_math/mcp_decorator.py
chuk_mcp_math/mcp_pydantic_base.py
chuk_mcp_math/sequences.py
chuk_mcp_math/arithmetic/__init__.py
chuk_mcp_math/arithmetic/comparison/__init__.py
chuk_mcp_math/arithmetic/comparison/extrema.py
chuk_mcp_math/arithmetic/comparison/relational.py
chuk_mcp_math/arithmetic/comparison/tolerance.py
chuk_mcp_math/arithmetic/core/__init__.py
chuk_mcp_math/arithmetic/core/basic_operations.py
chuk_mcp_math/arithmetic/core/modular.py
chuk_mcp_math/arithmetic/core/rounding.py
chuk_mcp_math/calculus/__init__.py
chuk_mcp_math/calculus/derivatives.py
chuk_mcp_math/calculus/integration.py
chuk_mcp_math/calculus/root_finding.py
chuk_mcp_math/cli/__init__.py
chuk_mcp_math/cli/main.py
chuk_mcp_math/geometry/__init__.py
chuk_mcp_math/geometry/distances.py
chuk_mcp_math/geometry/intersections.py
chuk_mcp_math/geometry/shapes.py
chuk_mcp_math/linear_algebra/__init__.py
chuk_mcp_math/linear_algebra/matrices/__init__.py
chuk_mcp_math/linear_algebra/matrices/operations.py
chuk_mcp_math/linear_algebra/matrices/solvers.py
chuk_mcp_math/linear_algebra/vectors/__init__.py
chuk_mcp_math/linear_algebra/vectors/geometric.py
chuk_mcp_math/linear_algebra/vectors/norms.py
chuk_mcp_math/linear_algebra/vectors/operations.py
chuk_mcp_math/linear_algebra/vectors/projections.py
chuk_mcp_math/number_theory/__init__.py
chuk_mcp_math/number_theory/advanced_primality.py
chuk_mcp_math/number_theory/advanced_prime_patterns.py
chuk_mcp_math/number_theory/arithmetic_functions.py
chuk_mcp_math/number_theory/basic_sequences.py
chuk_mcp_math/number_theory/combinatorial_numbers.py
chuk_mcp_math/number_theory/continued_fractions.py
chuk_mcp_math/number_theory/digital_operations.py
chuk_mcp_math/number_theory/diophantine_equations.py
chuk_mcp_math/number_theory/divisibility.py
chuk_mcp_math/number_theory/egyptian_fractions.py
chuk_mcp_math/number_theory/farey_sequences.py
chuk_mcp_math-0.2.3.dist-info/METADATA
chuk_mcp_math-0.2.3.dist-info/WHEEL
chuk_mcp_math-0.2.3.dist-info/top_level.txt
chuk_mcp_math-0.2.3.dist-info/RECORD
