Metadata-Version: 2.4
Name: chuk-mcp-math
Version: 0.2.3
Summary: Comprehensive MCP function library for AI models
Requires-Python: >=3.11
Provides-Extra: pydantic
Requires-Dist: pydantic>=2.11.1; extra == "pydantic"
Provides-Extra: dev
Requires-Dist: pytest>=7.0.0; extra == "dev"
Requires-Dist: pytest-asyncio>=0.21.0; extra == "dev"
Requires-Dist: pytest-cov>=4.0.0; extra == "dev"
Requires-Dist: pytest-mock>=3.10.0; extra == "dev"
Requires-Dist: hypothesis>=6.70.0; extra == "dev"
Requires-Dist: black>=23.0.0; extra == "dev"
Requires-Dist: flake8>=6.0.0; extra == "dev"
Requires-Dist: ruff>=0.8.0; extra == "dev"
Requires-Dist: mypy>=1.0.0; extra == "dev"
